[
    {
        "id": 5649157,
        "title": "Brandi Carlile",
        "category": "konser",
        "address": "1122 N. Milpas St.",
        "location": {
            "lat": 34.4327,
            "lon": -119.694
        },
        "venue": "Santa Barbara Bowl",
        "images": {
            "huge": "https://seatgeek.com/images/performers-landscape/brandi-carlile-bbbc02/363/25190/huge.jpg"
        },
        "date_time_local": "2022-06-21T03:30:00",
        "tbd": true,
        "performers_name": "Brandi Carlile",
        "state": "CA",
        "url": "/5649157",
        "price": [
            86.5,
            33.3,
            89.3,
            45.4,
            45.5
        ]
    },
    {
        "id": 5538078,
        "title": "Bon Iver",
        "category": "konser",
        "address": "101 West 4th Street",
        "location": {
            "lat": 39.0915,
            "lon": -84.4976
        },
        "venue": "PromoWest Pavilion at OVATION",
        "images": {
            "huge": "https://seatgeek.com/images/performers-landscape/bon-iver-502096/345/25187/huge.jpg"
        },
        "date_time_local": "2022-06-21T17:30:00",
        "tbd": false,
        "performers_name": "Bon Iver",
        "state": "KY",
        "url": "/5538078",
        "price": [
            74.0,
            29.0,
            65.0
        ]
    },
    {
        "id": 5671361,
        "title": "The Rare Occasions",
        "category": "konser",
        "address": "217 East Houston Street",
        "location": {
            "lat": 40.7222,
            "lon": -73.9867
        },
        "venue": "Mercury Lounge",
        "images": {
            "huge": "https://seatgeek.com/images/performers-landscape/generic-concerts-af2fe3/677165/35972/huge.jpg"
        },
        "date_time_local": "2022-06-21T18:00:00",
        "tbd": false,
        "performers_name": "The Rare Occasions",
        "state": "NY",
        "url": "/5671361",
        "price": [
            24.7,
            75.9
        ]
    },
    {
        "id": 5632262,
        "title": "Rex Orange County",
        "category": "konser",
        "address": "400 North Shore Drive",
        "location": {
            "lat": 40.4461,
            "lon": -80.0123
        },
        "venue": "Stage AE",
        "images": {
            "huge": "https://seatgeek.com/images/performers-landscape/rex-orange-county-c45ef2/609177/20786/huge.jpg"
        },
        "date_time_local": "2022-06-21T18:00:00",
        "tbd": false,
        "performers_name": "Rex Orange County",
        "state": "PA",
        "url": "/5632262",
        "price": [
            54.8,
            54.2,
            43.6,
            69.8,
            82.0
        ]
    },
    {
        "id": 5685236,
        "title": "Crown The Empire",
        "category": "konser",
        "address": "735 Queen Street East",
        "location": {
            "lat": 43.6588,
            "lon": -79.3487
        },
        "venue": "The Opera House",
        "images": {
            "huge": "https://seatgeek.com/images/performers-landscape/crown-the-empire-9506e9/61966/huge.jpg"
        },
        "date_time_local": "2022-06-21T18:00:00",
        "tbd": false,
        "performers_name": "Crown The Empire",
        "state": "ON",
        "url": "/5685236",
        "price": [
            48.5,
            52.0,
            89.5,
            80.3
        ]
    },
    {
        "id": 5671072,
        "title": "Flogging Molly and The Interrupters",
        "category": "konser",
        "address": "500 South McDowell Street",
        "location": {
            "lat": 35.7738,
            "lon": -78.6431
        },
        "venue": "Red Hat Amphitheater",
        "images": {
            "huge": "https://seatgeek.com/images/performers-landscape/flogging-molly-b95647/741/15988/huge.jpg"
        },
        "date_time_local": "2022-06-21T18:00:00",
        "tbd": false,
        "performers_name": "Flogging Molly",
        "state": "NC",
        "url": "/5671072",
        "price": [
            30.2,
            71.6
        ]
    },
    {
        "id": 5414990,
        "title": "Patti LaBelle",
        "category": "konser",
        "address": "450 South 4th St.",
        "location": {
            "lat": 43.1655,
            "lon": -79.0453
        },
        "venue": "Artpark Amphitheatre",
        "images": {
            "huge": "https://seatgeek.com/images/performers-landscape/patti-labelle-b3d127/1401/24929/huge.jpg"
        },
        "date_time_local": "2022-06-21T18:30:00",
        "tbd": false,
        "performers_name": "Patti LaBelle",
        "state": "NY",
        "url": "/5414990",
        "price": [
            84.4,
            67.1
        ]
    },
    {
        "id": 5650967,
        "title": "My Morning Jacket",
        "category": "konser",
        "address": "2014 Sycamore Street",
        "location": {
            "lat": 41.4963,
            "lon": -81.7029
        },
        "venue": "Jacobs Pavilion at Nautica",
        "images": {
            "huge": "https://seatgeek.com/images/performers-landscape/my-morning-jacket-984ce2/1307/huge.jpg"
        },
        "date_time_local": "2022-06-21T18:30:00",
        "tbd": false,
        "performers_name": "My Morning Jacket",
        "state": "OH",
        "url": "/5650967",
        "price": [
            77.2
        ]
    },
    {
        "id": 5673660,
        "title": "Machine Gun Kelly with Avril Lavigne and Iann Dior",
        "category": "konser",
        "address": "333 East Trade Street",
        "location": {
            "lat": 35.2248,
            "lon": -80.8403
        },
        "venue": "Spectrum Center",
        "images": {
            "huge": "https://seatgeek.com/images/performers-landscape/machine-gun-kelly-48827b/4711/huge.jpg"
        },
        "date_time_local": "2022-06-21T18:30:00",
        "tbd": false,
        "performers_name": "Machine Gun Kelly",
        "state": "NC",
        "url": "/5673660",
        "price": [
            53.4,
            37.1,
            55.2,
            40.4
        ]
    },
    {
        "id": 5629606,
        "title": "Tash Sultana",
        "category": "konser",
        "address": "425 Chartiers Ave.",
        "location": {
            "lat": 40.4646,
            "lon": -80.059
        },
        "venue": "Roxian Theatre",
        "images": {
            "huge": "https://seatgeek.com/images/performers-landscape/tash-sultana-64e4e0/428678/huge.jpg"
        },
        "date_time_local": "2022-06-21T18:30:00",
        "tbd": false,
        "performers_name": "Tash Sultana",
        "state": "PA",
        "url": "/5629606",
        "price": [
            76.1,
            45.3
        ]
    },
    {
        "id": 5667528,
        "title": "Maverick City Music with Kirk Franklin",
        "category": "konser",
        "address": "130 Fulton West",
        "location": {
            "lat": 42.9624,
            "lon": -85.6716
        },
        "venue": "Van Andel Arena",
        "images": {
            "huge": "https://seatgeek.com/images/performers-landscape/maverick-city-music-9c6123/794477/huge.jpg"
        },
        "date_time_local": "2022-06-21T18:45:00",
        "tbd": false,
        "performers_name": "Maverick City Music",
        "state": "MI",
        "url": "/5667528",
        "price": [
            82.9
        ]
    },
    {
        "id": 5699589,
        "title": "Penelope Scott",
        "category": "konser",
        "address": "50 Lower Alabama Street",
        "location": {
            "lat": 33.7515,
            "lon": -84.3899
        },
        "venue": "Masquerade (Purgatory)",
        "images": {
            "huge": "https://seatgeek.com/images/performers-landscape/penelope-scott-9cc7a0/797659/huge.jpg"
        },
        "date_time_local": "2022-06-21T19:00:00",
        "tbd": false,
        "performers_name": "Penelope Scott",
        "state": "GA",
        "url": "/5699589",
        "price": [
            47.5,
            77.0
        ]
    },
    {
        "id": 5675700,
        "title": "Bleachers",
        "category": "konser",
        "address": "343 E 25th Street",
        "location": {
            "lat": 41.2207,
            "lon": -111.972
        },
        "venue": "Ogden Amphitheater",
        "images": {
            "huge": "https://seatgeek.com/images/performers-landscape/bleachers-6aff68/211903/15457/huge.jpg"
        },
        "date_time_local": "2022-06-21T17:00:00",
        "tbd": false,
        "performers_name": "Bleachers",
        "state": "UT",
        "url": "/5675700",
        "price": [
            66.3,
            33.5,
            81.2,
            84.5,
            47.7
        ]
    },
    {
        "id": 5638526,
        "title": "Failure",
        "category": "konser",
        "address": "300 East Main Street",
        "location": {
            "lat": 35.9098,
            "lon": -79.0689
        },
        "venue": "Cat's Cradle",
        "images": {
            "huge": "https://seatgeek.com/images/performers-landscape/failure-d014b7/94263/7335/huge.jpg"
        },
        "date_time_local": "2022-06-21T19:00:00",
        "tbd": false,
        "performers_name": "Failure",
        "state": "NC",
        "url": "/5638526",
        "price": [
            53.1,
            66.4,
            23.3
        ]
    },
    {
        "id": 5661818,
        "title": "The Band Camino\t",
        "category": "konser",
        "address": "5000 Euclid Avenue",
        "location": {
            "lat": 41.5036,
            "lon": -81.6538
        },
        "venue": "Agora Theatre",
        "images": {
            "huge": "https://seatgeek.com/images/performers-landscape/the-band-camino-a97d34/430358/huge.jpg"
        },
        "date_time_local": "2022-06-21T19:00:00",
        "tbd": false,
        "performers_name": "The Band Camino",
        "state": "OH",
        "url": "/5661818",
        "price": [
            77.2,
            51.7,
            41.8,
            68.0
        ]
    },
    {
        "id": 5664418,
        "title": "Nathaniel Rateliff & The Night Sweats with Zach Bryan",
        "category": "konser",
        "address": "1340 A1a S",
        "location": {
            "lat": 29.8921,
            "lon": -81.3143
        },
        "venue": "St. Augustine Amphitheatre",
        "images": {
            "huge": "https://seatgeek.com/images/performers-landscape/nathaniel-rateliff-the-night-sweats-e4d30a/291820/huge.jpg"
        },
        "date_time_local": "2022-06-21T19:00:00",
        "tbd": false,
        "performers_name": "Nathaniel Rateliff & The Night Sweats",
        "state": "FL",
        "url": "/5664418",
        "price": [
            60.8,
            67.9,
            50.5,
            83.4
        ]
    },
    {
        "id": 5661257,
        "title": "Subsonic Eye",
        "category": "konser",
        "address": "939 Boylston Street",
        "location": {
            "lat": 42.3482,
            "lon": -71.0851
        },
        "venue": "Cafe 939",
        "images": {
            "huge": "https://seatgeek.com/images/performers-landscape/subsonic-eye-7442fc/796847/huge.jpg"
        },
        "date_time_local": "2022-06-21T19:00:00",
        "tbd": false,
        "performers_name": "Subsonic Eye",
        "state": "MA",
        "url": "/5661257",
        "price": [
            52.9
        ]
    },
    {
        "id": 5704694,
        "title": "Lawrence",
        "category": "konser",
        "address": "238 College Street",
        "location": {
            "lat": 41.3067,
            "lon": -72.9296
        },
        "venue": "College Street Music Hall",
        "images": {
            "huge": "https://seatgeek.com/images/performers-landscape/lawrence-dc87c8/121034/huge.jpg"
        },
        "date_time_local": "2022-06-21T19:00:00",
        "tbd": false,
        "performers_name": "Lawrence",
        "state": "CT",
        "url": "/5704694",
        "price": [
            45.2,
            40.8
        ]
    },
    {
        "id": 5626235,
        "title": "Denzel Curry",
        "category": "konser",
        "address": "1490 E Buena Vista Dr",
        "location": {
            "lat": 28.3684,
            "lon": -81.5224
        },
        "venue": "House of Blues - Orlando",
        "images": {
            "huge": "https://seatgeek.com/images/performers-landscape/denzel-curry-a5cfd2/267938/45964/huge.jpg"
        },
        "date_time_local": "2022-06-21T19:00:00",
        "tbd": false,
        "performers_name": "Denzel Curry",
        "state": "FL",
        "url": "/5626235",
        "price": [
            75.8,
            80.9
        ]
    },
    {
        "id": 5677390,
        "title": "Allegaeon with Aenimus",
        "category": "konser",
        "address": "2105 South State Street",
        "location": {
            "lat": 41.8539,
            "lon": -87.6269
        },
        "venue": "Reggies Chicago",
        "images": {
            "huge": "https://seatgeek.com/images/performers-landscape/generic-concerts-af2fe3/677165/35972/huge.jpg"
        },
        "date_time_local": "2022-06-21T18:00:00",
        "tbd": false,
        "performers_name": "Allegaeon",
        "state": "IL",
        "url": "/5677390",
        "price": [
            46.8,
            54.9,
            61.0,
            54.3
        ]
    },
    {
        "id": 5673028,
        "title": "Lake Street Dive",
        "category": "konser",
        "address": "31806 Lakeview Drive",
        "location": {
            "lat": 38.4665,
            "lon": -75.1118
        },
        "venue": "Freeman Arts Pavilion",
        "images": {
            "huge": "https://seatgeek.com/images/performers-landscape/lake-street-dive-ff1ded/32475/huge.jpg"
        },
        "date_time_local": "2022-06-21T19:00:00",
        "tbd": false,
        "performers_name": "Lake Street Dive",
        "state": "DE",
        "url": "/5673028",
        "price": [
            30.4,
            35.7,
            74.4,
            54.6,
            77.0
        ]
    },
    {
        "id": 5547281,
        "title": "The Masked Singer Live",
        "category": "konser",
        "address": "7750 Capital 1 Tower Rd",
        "location": {
            "lat": 38.9254,
            "lon": -77.2113
        },
        "venue": "Capital One Hall",
        "images": {
            "huge": "https://seatgeek.com/images/performers-landscape/generic-concerts-af2fe3/677165/35972/huge.jpg"
        },
        "date_time_local": "2022-06-21T19:30:00",
        "tbd": false,
        "performers_name": "The Masked Singer Live",
        "state": "VA",
        "url": "/5547281",
        "price": [
            82.9
        ]
    },
    {
        "id": 5686175,
        "title": "The Blue Stones with Des Rocs",
        "category": "konser",
        "address": "29 E Allen Street",
        "location": {
            "lat": 39.9656,
            "lon": -75.1351
        },
        "venue": "The Foundry",
        "images": {
            "huge": "https://seatgeek.com/images/performers-landscape/the-blue-stones-e8aeb3/403532/24910/huge.jpg"
        },
        "date_time_local": "2022-06-21T19:30:00",
        "tbd": false,
        "performers_name": "The Blue Stones",
        "state": "PA",
        "url": "/5686175",
        "price": [
            29.6,
            68.7
        ]
    },
    {
        "id": 5591891,
        "title": "Jack Johnson With Durand Jones & The Indications",
        "category": "konser",
        "address": "72 Meadowbrook Lane",
        "location": {
            "lat": 43.5801,
            "lon": -71.4129
        },
        "venue": "Bank of New Hampshire Pavilion",
        "images": {
            "huge": "https://seatgeek.com/images/performers-landscape/jack-johnson-bae00f/2414/huge.jpg"
        },
        "date_time_local": "2022-06-21T19:30:00",
        "tbd": false,
        "performers_name": "Jack Johnson",
        "state": "NH",
        "url": "/5591891",
        "price": [
            23.8,
            49.0
        ]
    },
    {
        "id": 5714396,
        "title": "Trey Anastasio",
        "category": "konser",
        "address": "4000 Highway M",
        "location": {
            "lat": 44.6553,
            "lon": -85.1752
        },
        "venue": "Kresge Auditorium",
        "images": {
            "huge": "https://seatgeek.com/images/performers-landscape/trey-anastasio-4d430c/1943/huge.jpg"
        },
        "date_time_local": "2022-06-21T19:30:00",
        "tbd": false,
        "performers_name": "Trey Anastasio",
        "state": "MI",
        "url": "/5714396",
        "price": [
            53.9,
            61.2
        ]
    },
    {
        "id": 5319871,
        "title": "Happy Together Tour (Rescheduled from 6/23/2020, 9/3/2020, 6/22/2021)",
        "category": "konser",
        "address": "21 West Main Street",
        "location": {
            "lat": 41.6472,
            "lon": -70.2985
        },
        "venue": "Cape Cod Melody Tent",
        "images": {
            "huge": "https://seatgeek.com/images/performers-landscape/generic-concerts-af2fe3/677165/35972/huge.jpg"
        },
        "date_time_local": "2022-06-21T19:30:00",
        "tbd": false,
        "performers_name": "The Cowsills",
        "state": "MA",
        "url": "/5319871",
        "price": [
            39.2
        ]
    },
    {
        "id": 5186122,
        "title": "Steely Dan",
        "category": "konser",
        "address": "108 Avenue of the Pines",
        "location": {
            "lat": 43.0554,
            "lon": -73.8059
        },
        "venue": "Saratoga Performing Arts Center",
        "images": {
            "huge": "https://seatgeek.com/images/performers-landscape/steely-dan-04698b/1683/13677/huge.jpg"
        },
        "date_time_local": "2022-06-21T19:30:00",
        "tbd": false,
        "performers_name": "Steely Dan",
        "state": "NY",
        "url": "/5186122",
        "price": [
            27.9,
            41.5,
            44.8,
            30.5,
            47.3
        ]
    },
    {
        "id": 5680185,
        "title": "Adekunle Gold",
        "category": "konser",
        "address": "329 N Dearborn St",
        "location": {
            "lat": 41.8883,
            "lon": -87.6288
        },
        "venue": "House of Blues Chicago",
        "images": {
            "huge": "https://seatgeek.com/images/performers-landscape/adekunle-gold-78797e/639315/huge.jpg"
        },
        "date_time_local": "2022-06-21T18:30:00",
        "tbd": false,
        "performers_name": "Adekunle Gold",
        "state": "IL",
        "url": "/5680185",
        "price": [
            34.6,
            28.4
        ]
    },
    {
        "id": 5683703,
        "title": "Tiny Moving Parts with This Wild Life",
        "category": "konser",
        "address": "600 Nevan Road",
        "location": {
            "lat": 36.8493,
            "lon": -76.0194
        },
        "venue": "Elevation 27",
        "images": {
            "huge": "https://seatgeek.com/images/performers-landscape/tiny-moving-parts-b38000/270685/huge.jpg"
        },
        "date_time_local": "2022-06-21T19:30:00",
        "tbd": false,
        "performers_name": "Tiny Moving Parts",
        "state": "VA",
        "url": "/5683703",
        "price": [
            28.9,
            39.6
        ]
    },
    {
        "id": 5686811,
        "title": "Jackyl",
        "category": "konser",
        "address": "300 York Street",
        "location": {
            "lat": 41.308,
            "lon": -72.9244
        },
        "venue": "Toad's Place",
        "images": {
            "huge": "https://seatgeek.com/images/performers-landscape/jackyl-04b632/902/huge.jpg"
        },
        "date_time_local": "2022-06-21T19:30:00",
        "tbd": false,
        "performers_name": "Jackyl",
        "state": "CT",
        "url": "/5686811",
        "price": [
            22.4,
            71.4,
            55.1,
            56.8,
            49.6
        ]
    },
    {
        "id": 5729550,
        "title": "Womens PGA Championship - Weekly Pass",
        "category": "spor",
        "address": "8500 River Rd",
        "location": {
            "lat": 38.9963,
            "lon": -77.1764
        },
        "venue": "Congressional Country Club",
        "images": {
            "huge": "https://seatgeek.com/images/performers-landscape/kpmg-women-s-pga-championship-d3e4ed/451845/huge.jpg"
        },
        "date_time_local": "2022-06-21T03:30:00",
        "tbd": true,
        "performers_name": "KPMG Women's PGA Championship",
        "state": "MD",
        "url": "/5729550",
        "price": [
            38.8,
            77.5,
            88.3,
            39.0
        ]
    },
    {
        "id": 5592648,
        "title": "St. Lucie Mets at Palm Beach Cardinals",
        "category": "spor",
        "address": "4751 Main Street",
        "location": {
            "lat": 26.8911,
            "lon": -80.1163
        },
        "venue": "Roger Dean Stadium",
        "images": {
            "huge": "https://seatgeek.com/images/performers-landscape/palm-beach-cardinals-4b9faf/9420/huge.jpg"
        },
        "date_time_local": "2022-06-21T03:30:00",
        "tbd": true,
        "performers_name": "Palm Beach Cardinals",
        "state": "FL",
        "url": "/5592648",
        "price": [
            67.3,
            65.2
        ]
    },
    {
        "id": 5565434,
        "title": "Hudson Valley Renegades at Winston-Salem Dash",
        "category": "spor",
        "address": "951 Ballpark Way",
        "location": {
            "lat": 36.0996,
            "lon": -80.2411
        },
        "venue": "BB&T Ballpark",
        "images": {
            "huge": "https://seatgeek.com/images/performers-landscape/winston-salem-dash-75a579/9413/huge.jpg"
        },
        "date_time_local": "2022-06-21T03:30:00",
        "tbd": true,
        "performers_name": "Winston-Salem Dash",
        "state": "NC",
        "url": "/5565434",
        "price": [
            74.2,
            21.8,
            76.4
        ]
    },
    {
        "id": 5590684,
        "title": "Aberdeen IronBirds at Wilmington Blue Rocks",
        "category": "spor",
        "address": "801 Shipyard Drive",
        "location": {
            "lat": 39.73,
            "lon": -75.56
        },
        "venue": "Frawley Stadium",
        "images": {
            "huge": "https://seatgeek.com/images/performers-landscape/generic-minor-league-baseball-9c1f76/677210/35944/huge.jpg"
        },
        "date_time_local": "2022-06-21T03:30:00",
        "tbd": true,
        "performers_name": "Wilmington Blue Rocks",
        "state": "DE",
        "url": "/5590684",
        "price": [
            54.9,
            65.9,
            70.1,
            30.7
        ]
    },
    {
        "id": 5679273,
        "title": "San Antonio Missions at Wichita Wind Surge",
        "category": "spor",
        "address": "300 S Sycamore St",
        "location": {
            "lat": 37.6816,
            "lon": -97.3452
        },
        "venue": "Riverfront Stadium",
        "images": {
            "huge": "https://seatgeek.com/images/performers-landscape/wichita-wind-surge-2b59e7/773608/huge.jpg"
        },
        "date_time_local": "2022-06-21T03:30:00",
        "tbd": true,
        "performers_name": "Wichita Wind Surge",
        "state": "KS",
        "url": "/5679273",
        "price": [
            24.7,
            43.1,
            70.7,
            68.8
        ]
    },
    {
        "id": 5557894,
        "title": "Rainiers at Space Cowboys",
        "category": "spor",
        "address": "1 Stadium Drive",
        "location": {
            "lat": 29.6224,
            "lon": -95.6473
        },
        "venue": "Constellation Field",
        "images": {
            "huge": "https://seatgeek.com/images/performers-landscape/generic-minor-league-baseball-9c1f76/677210/35944/huge.jpg"
        },
        "date_time_local": "2022-06-21T03:30:00",
        "tbd": true,
        "performers_name": "Sugar Land Space Cowboys",
        "state": "TX",
        "url": "/5557894",
        "price": [
            53.7,
            48.3
        ]
    },
    {
        "id": 5589994,
        "title": "Rancho Cucamonga Quakes at Lake Elsinore Storm",
        "category": "spor",
        "address": "500 Diamond Drive",
        "location": {
            "lat": 33.6547,
            "lon": -117.303
        },
        "venue": "Lake Elsinore Diamond",
        "images": {
            "huge": "https://seatgeek.com/images/performers-landscape/generic-minor-league-baseball-9c1f76/677210/35944/huge.jpg"
        },
        "date_time_local": "2022-06-21T03:30:00",
        "tbd": true,
        "performers_name": "Lake Elsinore Storm",
        "state": "CA",
        "url": "/5589994",
        "price": [
            81.9,
            41.3,
            38.5
        ]
    },
    {
        "id": 5557571,
        "title": "El Paso Chihuahuas at Sacramento River Cats",
        "category": "spor",
        "address": "400 Ballpark Drive",
        "location": {
            "lat": 38.5804,
            "lon": -121.514
        },
        "venue": "Sutter Health Park",
        "images": {
            "huge": "https://seatgeek.com/images/performers-landscape/sacramento-river-cats-20384c/9258/huge.jpg"
        },
        "date_time_local": "2022-06-21T03:30:00",
        "tbd": true,
        "performers_name": "Sacramento River Cats",
        "state": "CA",
        "url": "/5557571",
        "price": [
            46.7,
            74.9
        ]
    },
    {
        "id": 5572139,
        "title": "U.S. Senior Open - Weekly Gallery Package (6/21 - 6/26)",
        "category": "spor",
        "address": "2050 Saucon Valley Rd",
        "location": {
            "lat": 40.56,
            "lon": -75.38
        },
        "venue": "Saucon Valley Country Club",
        "images": {
            "huge": "https://seatgeek.com/images/performers-landscape/us-senior-open-golf-03faed/5771/huge.jpg"
        },
        "date_time_local": "2022-06-21T03:30:00",
        "tbd": true,
        "performers_name": "US Senior Open Golf",
        "state": "PA",
        "url": "/5572139",
        "price": [
            31.8,
            34.3,
            72.4
        ]
    },
    {
        "id": 5605930,
        "title": "Williamsport Crosscutters at West Virginia Black Bears",
        "category": "spor",
        "address": "1 University Town Center Drive",
        "location": {
            "lat": 39.6437,
            "lon": -79.9959
        },
        "venue": "Monongalia County Ballpark",
        "images": {
            "huge": "https://seatgeek.com/images/performers-landscape/generic-minor-league-baseball-9c1f76/677210/35944/huge.jpg"
        },
        "date_time_local": "2022-06-21T13:00:00",
        "tbd": false,
        "performers_name": "West Virginia Black Bears",
        "state": "WV",
        "url": "/5605930",
        "price": [
            67.8,
            33.7,
            60.3,
            77.5,
            35.0
        ]
    },
    {
        "id": 5614642,
        "title": "Frederick Keys at State College Spikes",
        "category": "spor",
        "address": "701 Porter Road",
        "location": {
            "lat": 40.8123,
            "lon": -77.8529
        },
        "venue": "Medlar Field At Lubrano Park",
        "images": {
            "huge": "https://seatgeek.com/images/performers-landscape/generic-minor-league-baseball-9c1f76/677210/35944/huge.jpg"
        },
        "date_time_local": "2022-06-21T13:00:00",
        "tbd": false,
        "performers_name": "State College Spikes",
        "state": "PA",
        "url": "/5614642",
        "price": [
            21.4,
            77.1
        ]
    },
    {
        "id": 5580829,
        "title": "Peoria Chiefs at South Bend Cubs",
        "category": "spor",
        "address": "501 West South Street",
        "location": {
            "lat": 41.6703,
            "lon": -86.2556
        },
        "venue": "Four Winds Field at Coveleski Stadium",
        "images": {
            "huge": "https://seatgeek.com/images/performers-landscape/south-bend-cubs-ecbdcd/9288/huge.jpg"
        },
        "date_time_local": "2022-06-21T13:00:00",
        "tbd": false,
        "performers_name": "South Bend Cubs",
        "state": "IN",
        "url": "/5580829",
        "price": [
            21.0,
            74.7,
            40.3
        ]
    },
    {
        "id": 5614545,
        "title": "Trois Rivieres Aigles at Tri-City ValleyCats",
        "category": "spor",
        "address": "80 Vandenburg Avenue",
        "location": {
            "lat": 42.6973,
            "lon": -73.682
        },
        "venue": "Joseph L. Bruno Stadium",
        "images": {
            "huge": "https://seatgeek.com/images/performers-landscape/tri-city-valleycats-74d3c7/9226/huge.jpg"
        },
        "date_time_local": "2022-06-21T13:00:00",
        "tbd": false,
        "performers_name": "Tri-City ValleyCats",
        "state": "NY",
        "url": "/5614545",
        "price": [
            36.9,
            41.3,
            40.7,
            21.5,
            27.0
        ]
    },
    {
        "id": 5581130,
        "title": "Jupiter Hammerheads at Daytona Tortugas",
        "category": "spor",
        "address": "105 East Orange Avenue",
        "location": {
            "lat": 29.2091,
            "lon": -81.0154
        },
        "venue": "Jackie Robinson Ballpark",
        "images": {
            "huge": "https://seatgeek.com/images/performers-landscape/daytona-tortugas-32dbef/9927/huge.jpg"
        },
        "date_time_local": "2022-06-21T13:00:00",
        "tbd": false,
        "performers_name": "Daytona Tortugas",
        "state": "FL",
        "url": "/5581130",
        "price": [
            78.1
        ]
    },
    {
        "id": 5614536,
        "title": "Trenton Thunder at Mahoning Valley Scrappers",
        "category": "spor",
        "address": "111 Eastwood Mall Blvd",
        "location": {
            "lat": 41.2186,
            "lon": -80.755
        },
        "venue": "Eastwood Field",
        "images": {
            "huge": "https://seatgeek.com/images/performers-landscape/generic-minor-league-baseball-9c1f76/677210/35944/huge.jpg"
        },
        "date_time_local": "2022-06-21T13:00:00",
        "tbd": false,
        "performers_name": "Mahoning Valley Scrappers",
        "state": "OH",
        "url": "/5614536",
        "price": [
            82.1,
            41.8,
            38.4,
            25.7
        ]
    },
    {
        "id": 5575810,
        "title": "Beloit Snappers at Lansing Lugnuts",
        "category": "spor",
        "address": "505 East Michigan Avenue",
        "location": {
            "lat": 42.7342,
            "lon": -84.5456
        },
        "venue": "Jackson Field",
        "images": {
            "huge": "https://seatgeek.com/images/performers-landscape/generic-minor-league-baseball-9c1f76/677210/35944/huge.jpg"
        },
        "date_time_local": "2022-06-21T13:00:00",
        "tbd": false,
        "performers_name": "Lansing Lugnuts",
        "state": "MI",
        "url": "/5575810",
        "price": [
            40.8,
            53.0,
            31.9,
            28.4,
            25.0
        ]
    },
    {
        "id": 5549825,
        "title": "Columbus Clippers at Omaha Storm Chasers",
        "category": "spor",
        "address": "12356 Ballpark Way",
        "location": {
            "lat": 41.1509,
            "lon": -96.1059
        },
        "venue": "Werner Park",
        "images": {
            "huge": "https://seatgeek.com/images/performers-landscape/omaha-storm-chasers-2f02e1/9321/huge.jpg"
        },
        "date_time_local": "2022-06-21T12:05:00",
        "tbd": false,
        "performers_name": "Omaha Storm Chasers",
        "state": "NE",
        "url": "/5549825",
        "price": [
            26.3,
            74.9,
            61.4
        ]
    },
    {
        "id": 5487316,
        "title": "CWS - Gm 9 (Texas A&M vs Notre Dame)",
        "category": "spor",
        "address": "1200 Mike Fahey St",
        "location": {
            "lat": 41.2664,
            "lon": -95.9325
        },
        "venue": "Charles Schwab Field Omaha",
        "images": {
            "huge": "https://seatgeek.com/images/performers-landscape/ncaa-college-world-series-daab9e/10529/huge.jpg"
        },
        "date_time_local": "2022-06-21T13:00:00",
        "tbd": false,
        "performers_name": "NCAA College World Series\t",
        "state": "NE",
        "url": "/5487316",
        "price": [
            31.1,
            58.0
        ]
    },
    {
        "id": 5574172,
        "title": "Bowie Baysox at Erie SeaWolves",
        "category": "spor",
        "address": "110 E 10th St.",
        "location": {
            "lat": 42.1271,
            "lon": -80.0802
        },
        "venue": "UPMC Park",
        "images": {
            "huge": "https://seatgeek.com/images/performers-landscape/erie-seawolves-82c148/9293/huge.jpg"
        },
        "date_time_local": "2022-06-21T18:05:00",
        "tbd": false,
        "performers_name": "Erie SeaWolves",
        "state": "PA",
        "url": "/5574172",
        "price": [
            49.2,
            42.3,
            22.8,
            20.9,
            81.2
        ]
    },
    {
        "id": 5576429,
        "title": "Bradenton Marauders at Dunedin Blue Jays",
        "category": "spor",
        "address": "373 Douglas Ave.",
        "location": {
            "lat": 28.0036,
            "lon": -82.7868
        },
        "venue": "TD Ballpark",
        "images": {
            "huge": "https://seatgeek.com/images/performers-landscape/dunedin-blue-jays-5ce8ad/9924/huge.jpg"
        },
        "date_time_local": "2022-06-21T18:05:00",
        "tbd": false,
        "performers_name": "Dunedin Blue Jays",
        "state": "FL",
        "url": "/5576429",
        "price": [
            60.1,
            59.4,
            40.6
        ]
    },
    {
        "id": 5586536,
        "title": "Asheville Tourists at Greensboro Grasshoppers",
        "category": "spor",
        "address": "408 Bellemeade Street",
        "location": {
            "lat": 36.08,
            "lon": -79.79
        },
        "venue": "First National Bank Field",
        "images": {
            "huge": "https://seatgeek.com/images/performers-landscape/greensboro-grasshoppers-636192/9330/huge.jpg"
        },
        "date_time_local": "2022-06-21T18:30:00",
        "tbd": false,
        "performers_name": "Greensboro Grasshoppers",
        "state": "NC",
        "url": "/5586536",
        "price": [
            51.4,
            67.6
        ]
    },
    {
        "id": 5572597,
        "title": "Clearwater Threshers at Tampa Tarpons",
        "category": "spor",
        "address": "1 Steinbrenner Drive",
        "location": {
            "lat": 27.9798,
            "lon": -82.5072
        },
        "venue": "George M. Steinbrenner Field",
        "images": {
            "huge": "https://seatgeek.com/images/performers-landscape/tampa-tarpons-7e0e46/9916/4610/huge.jpg"
        },
        "date_time_local": "2022-06-21T18:30:00",
        "tbd": false,
        "performers_name": "Tampa Tarpons",
        "state": "FL",
        "url": "/5572597",
        "price": [
            86.9,
            68.2,
            50.9,
            28.7
        ]
    },
    {
        "id": 5574019,
        "title": "Fort Myers Mighty Mussels at Lakeland Flying Tigers",
        "category": "spor",
        "address": "2301 Lakeland Hills Blvd.",
        "location": {
            "lat": 28.0739,
            "lon": -81.9533
        },
        "venue": "Joker Marchant Stadium",
        "images": {
            "huge": "https://seatgeek.com/images/performers-landscape/lakeland-flying-tigers-e954f4/9431/huge.jpg"
        },
        "date_time_local": "2022-06-21T18:30:00",
        "tbd": false,
        "performers_name": "Lakeland Flying Tigers",
        "state": "FL",
        "url": "/5574019",
        "price": [
            80.8,
            56.5,
            26.7,
            64.7
        ]
    },
    {
        "id": 5567041,
        "title": "Harrisburg Senators at Akron RubberDucks",
        "category": "spor",
        "address": "300 South Main Street",
        "location": {
            "lat": 41.0774,
            "lon": -81.5215
        },
        "venue": "Canal Park",
        "images": {
            "huge": "https://seatgeek.com/images/performers-landscape/akron-rubberducks-47f88b/9252/huge.jpg"
        },
        "date_time_local": "2022-06-21T18:35:00",
        "tbd": false,
        "performers_name": "Akron RubberDucks",
        "state": "OH",
        "url": "/5567041",
        "price": [
            67.0
        ]
    },
    {
        "id": 5582146,
        "title": "Reading Phillies at Rumble Ponies",
        "category": "spor",
        "address": "211 Henry Street",
        "location": {
            "lat": 42.1024,
            "lon": -75.9049
        },
        "venue": "Mirabito Stadium",
        "images": {
            "huge": "https://seatgeek.com/images/performers-landscape/binghamton-mets-d343e8/9263/huge.jpg"
        },
        "date_time_local": "2022-06-21T18:35:00",
        "tbd": false,
        "performers_name": "Binghamton Mets",
        "state": "NY",
        "url": "/5582146",
        "price": [
            39.5,
            88.2,
            82.2,
            89.2
        ]
    },
    {
        "id": 5594272,
        "title": "Portland Sea Dogs at Richmond Flying Squirrels",
        "category": "spor",
        "address": "3001 N Boulevard",
        "location": {
            "lat": 37.5718,
            "lon": -77.4642
        },
        "venue": "The Diamond",
        "images": {
            "huge": "https://seatgeek.com/images/performers-landscape/richmond-flying-squirrels-2db8cc/9274/huge.jpg"
        },
        "date_time_local": "2022-06-21T18:35:00",
        "tbd": false,
        "performers_name": "Richmond Flying Squirrels",
        "state": "VA",
        "url": "/5594272",
        "price": [
            51.2,
            24.3,
            35.8
        ]
    },
    {
        "id": 5462337,
        "title": "Dodgers at Reds",
        "category": "spor",
        "address": "100 Joe Nuxhall Way",
        "location": {
            "lat": 39.0974,
            "lon": -84.5071
        },
        "venue": "Great American Ball Park",
        "images": {
            "huge": "https://seatgeek.com/images/performers-landscape/cincinnati-reds-d89871/26/huge.jpg"
        },
        "date_time_local": "2022-06-21T18:40:00",
        "tbd": false,
        "performers_name": "Cincinnati Reds",
        "state": "OH",
        "url": "/5462337",
        "price": [
            62.9
        ]
    },
    {
        "id": 5520970,
        "title": "Charlotte Knights at Worcester Red Sox",
        "category": "spor",
        "address": "122 Madison Street",
        "location": {
            "lat": 42.2584,
            "lon": -71.8034
        },
        "venue": "Polar Park",
        "images": {
            "huge": "https://seatgeek.com/images/performers-landscape/worcester-red-sox-2893da/9249/huge.jpg"
        },
        "date_time_local": "2022-06-21T18:45:00",
        "tbd": false,
        "performers_name": "Worcester Red Sox",
        "state": "MA",
        "url": "/5520970",
        "price": [
            76.7,
            71.6
        ]
    },
    {
        "id": 5613192,
        "title": "Lexington County Blowfish at Savannah Bananas",
        "category": "spor",
        "address": "1401 East Victory Drive",
        "location": {
            "lat": 32.0454,
            "lon": -81.079
        },
        "venue": "Grayson Stadium",
        "images": {
            "huge": "https://seatgeek.com/images/performers-landscape/generic-sports-b33da4/677214/35941/huge.jpg"
        },
        "date_time_local": "2022-06-21T19:00:00",
        "tbd": false,
        "performers_name": "Savannah Bananas",
        "state": "GA",
        "url": "/5613192",
        "price": [
            53.6,
            27.7,
            70.0
        ]
    },
    {
        "id": 5595516,
        "title": " Dallas Wings at Atlanta Dream",
        "category": "spor",
        "address": "2000 Convention Center Concourse",
        "location": {
            "lat": 33.6456,
            "lon": -84.4576
        },
        "venue": "Gateway Center Arena at College Park",
        "images": {
            "huge": "https://seatgeek.com/images/performers-landscape/atlanta-dream-a6d185/10743/huge.jpg"
        },
        "date_time_local": "2022-06-21T19:00:00",
        "tbd": false,
        "performers_name": "Atlanta Dream",
        "state": "GA",
        "url": "/5595516",
        "price": [
            53.1,
            50.5,
            47.2,
            34.1
        ]
    },
    {
        "id": 5535818,
        "title": "Eiffel Tower Experience - Las Vegas",
        "category": "tiyatro",
        "address": "3655 Las Vegas Boulevard South",
        "location": {
            "lat": 36.1125,
            "lon": -115.171
        },
        "venue": "Le Theatre Des Arts at Paris Las Vegas",
        "images": {
            "huge": "https://seatgeek.com/images/performers-landscape/generic-family-entertainment-f800b0/677155/32439/huge.jpg"
        },
        "date_time_local": "2022-06-21T03:30:00",
        "tbd": true,
        "performers_name": "Eiffel Tower Experience",
        "state": "NV",
        "url": "/5535818",
        "price": [
            86.7,
            57.2,
            81.4
        ]
    },
    {
        "id": 5667408,
        "title": "Half-Stitched The Musical - Shipshewana",
        "category": "tiyatro",
        "address": "175 N Van Buren St",
        "location": {
            "lat": 41.6767,
            "lon": -85.5802
        },
        "venue": "Blue Gate Theatre",
        "images": {
            "huge": "https://seatgeek.com/images/performers-landscape/half-stitched-the-musical-83463a/678533/huge.jpg"
        },
        "date_time_local": "2022-06-21T13:00:00",
        "tbd": false,
        "performers_name": "Half-Stitched The Musical",
        "state": "IN",
        "url": "/5667408",
        "price": [
            74.0,
            51.1
        ]
    },
    {
        "id": 5705778,
        "title": "Richard III - Stratford",
        "category": "tiyatro",
        "address": "111 Lakeside Dr",
        "location": {
            "lat": 43.37,
            "lon": -80.98
        },
        "venue": "Tom Patterson Theatre",
        "images": {
            "huge": "https://seatgeek.com/images/performers-landscape/richard-iii-2aab7b/11176/huge.jpg"
        },
        "date_time_local": "2022-06-21T14:00:00",
        "tbd": false,
        "performers_name": "Richard III",
        "state": "ON",
        "url": "/5705778",
        "price": [
            69.6,
            27.9,
            63.9,
            73.4
        ]
    },
    {
        "id": 5502508,
        "title": "Mac King",
        "category": "tiyatro",
        "address": "3850 Las Vegas Blvd",
        "location": {
            "lat": 36.1,
            "lon": -115.17
        },
        "venue": "Tournament of Kings Arena at Excalibur Hotel and Casino",
        "images": {
            "huge": "https://seatgeek.com/images/performers-landscape/mac-king-3c4d1a/16551/5707/huge.jpg"
        },
        "date_time_local": "2022-06-21T13:00:00",
        "tbd": false,
        "performers_name": "Mac King",
        "state": "NV",
        "url": "/5502508",
        "price": [
            73.2,
            29.6,
            78.2,
            68.3
        ]
    },
    {
        "id": 5597094,
        "title": "Potted Potter - Las Vegas",
        "category": "tiyatro",
        "address": "3645 South Las Vegas Boulevard",
        "location": {
            "lat": 36.1142,
            "lon": -115.171
        },
        "venue": "The Magic Attic at Bally's Las Vegas",
        "images": {
            "huge": "https://seatgeek.com/images/performers-landscape/potted-potter-f98a7f/13876/huge.jpg"
        },
        "date_time_local": "2022-06-21T14:00:00",
        "tbd": false,
        "performers_name": "Potted Potter",
        "state": "NV",
        "url": "/5597094",
        "price": [
            54.5,
            58.2
        ]
    },
    {
        "id": 5588888,
        "title": "Cirque du Soleil Drawn to Life - Orlando",
        "category": "tiyatro",
        "address": "1751 Hotel Plaza Blvd",
        "location": {
            "lat": 28.373,
            "lon": -81.5107
        },
        "venue": "Walt Disney World Resort",
        "images": {
            "huge": "https://seatgeek.com/images/performers-landscape/generic-cirque-du-soleil-d09d27/677166/32438/huge.jpg"
        },
        "date_time_local": "2022-06-21T17:30:00",
        "tbd": false,
        "performers_name": "Cirque du Soleil Drawn to Life",
        "state": "FL",
        "url": "/5588888",
        "price": [
            87.1,
            69.9,
            61.9
        ]
    },
    {
        "id": 5646675,
        "title": "Paw Patrol Live - Salem",
        "category": "tiyatro",
        "address": "1001 Blvd",
        "location": {
            "lat": 37.2854,
            "lon": -80.0393
        },
        "venue": "Salem Civic Center",
        "images": {
            "huge": "https://seatgeek.com/images/performers-landscape/paw-patrol-live-613d60/514899/huge.jpg"
        },
        "date_time_local": "2022-06-21T18:00:00",
        "tbd": false,
        "performers_name": "Paw Patrol Live",
        "state": "VA",
        "url": "/5646675",
        "price": [
            75.6,
            67.2
        ]
    },
    {
        "id": 5674801,
        "title": "Blippi Live (not feat. Stevin John) - Warren",
        "category": "tiyatro",
        "address": "1703 Mahoning Avenue Northwest",
        "location": {
            "lat": 41.2514,
            "lon": -80.8302
        },
        "venue": "Packard Music Hall",
        "images": {
            "huge": "https://seatgeek.com/images/performers-landscape/blippi-live-not-feat-stevin-john-3caf99/772893/huge.jpg"
        },
        "date_time_local": "2022-06-21T18:00:00",
        "tbd": false,
        "performers_name": "Blippi Live (not feat. Stevin John)",
        "state": "OH",
        "url": "/5674801",
        "price": [
            79.5,
            49.1,
            88.6
        ]
    },
    {
        "id": 5642849,
        "title": "Spongebob Squarepants the Musical - Columbia",
        "category": "tiyatro",
        "address": "5900 Symphony Woods Rd",
        "location": {
            "lat": 39.2089,
            "lon": -76.8585
        },
        "venue": "Toby's Dinner Theatre",
        "images": {
            "huge": "https://seatgeek.com/images/performers-landscape/spongebob-squarepants-the-musical-8f279c/421170/huge.jpg"
        },
        "date_time_local": "2022-06-21T18:00:00",
        "tbd": false,
        "performers_name": "Spongebob Squarepants the Musical",
        "state": "MD",
        "url": "/5642849",
        "price": [
            45.9,
            72.4
        ]
    },
    {
        "id": 5502417,
        "title": "Mac King",
        "category": "tiyatro",
        "address": "3850 Las Vegas Blvd",
        "location": {
            "lat": 36.1,
            "lon": -115.17
        },
        "venue": "Tournament of Kings Arena at Excalibur Hotel and Casino",
        "images": {
            "huge": "https://seatgeek.com/images/performers-landscape/mac-king-3c4d1a/16551/5707/huge.jpg"
        },
        "date_time_local": "2022-06-21T15:00:00",
        "tbd": false,
        "performers_name": "Mac King",
        "state": "NV",
        "url": "/5502417",
        "price": [
            86.4,
            31.9,
            70.2,
            60.7,
            78.6
        ]
    },
    {
        "id": 5590839,
        "title": "Louis Jose Houde",
        "category": "tiyatro",
        "address": "1004 Rue Saint Catherine Street",
        "location": {
            "lat": 45.5004,
            "lon": -73.572
        },
        "venue": "L'Olympia (Olympia Theatre)",
        "images": {},
        "date_time_local": "2022-06-21T19:00:00",
        "tbd": false,
        "performers_name": "Louis Jose Houde",
        "state": "QC",
        "url": "/5590839",
        "price": [
            81.1,
            90.1
        ]
    },
    {
        "id": 5530354,
        "title": "Macbeth - New York",
        "category": "tiyatro",
        "address": "220 West 48th Street",
        "location": {
            "lat": 40.7605,
            "lon": -73.9857
        },
        "venue": "Longacre Theatre",
        "images": {
            "huge": "https://seatgeek.com/images/performers-landscape/macbeth-8cbdab/7481/27801/huge.jpg"
        },
        "date_time_local": "2022-06-21T19:00:00",
        "tbd": false,
        "performers_name": "Macbeth",
        "state": "NY",
        "url": "/5530354",
        "price": [
            38.8
        ]
    },
    {
        "id": 5692546,
        "title": "Neil Simon's Plaza Suite",
        "category": "tiyatro",
        "address": "145 West 44th Street",
        "location": {
            "lat": 40.7569,
            "lon": -73.9848
        },
        "venue": "Hudson Theatre",
        "images": {
            "huge": "https://seatgeek.com/images/performers-landscape/neil-simon-s-plaza-suite-05342a/793323/huge.jpg"
        },
        "date_time_local": "2022-06-21T19:00:00",
        "tbd": false,
        "performers_name": "Neil Simon's Plaza Suite",
        "state": "NY",
        "url": "/5692546",
        "price": [
            35.6
        ]
    },
    {
        "id": 5573560,
        "title": "Moulin Rouge! The Musical",
        "category": "tiyatro",
        "address": "302 West 45th Street",
        "location": {
            "lat": 40.7594,
            "lon": -73.9891
        },
        "venue": "Al Hirschfeld Theatre",
        "images": {
            "huge": "https://seatgeek.com/images/performers-landscape/moulin-rouge-the-musical-840f04/11509/huge.jpg"
        },
        "date_time_local": "2022-06-21T19:00:00",
        "tbd": false,
        "performers_name": "Moulin Rouge! The Musical",
        "state": "NY",
        "url": "/5573560",
        "price": [
            35.9,
            36.2,
            25.1
        ]
    },
    {
        "id": 5537481,
        "title": "Paradise Square",
        "category": "tiyatro",
        "address": "243 West 47th Street",
        "location": {
            "lat": 40.7602,
            "lon": -73.9862
        },
        "venue": "Barrymore Theatre",
        "images": {},
        "date_time_local": "2022-06-21T19:00:00",
        "tbd": false,
        "performers_name": "Paradise Square",
        "state": "NY",
        "url": "/5537481",
        "price": [
            23.7,
            83.9,
            51.1,
            49.8
        ]
    },
    {
        "id": 5528083,
        "title": "Menopause The Musical - Las Vegas",
        "category": "tiyatro",
        "address": "3475 Las Vegas Blvd S",
        "location": {
            "lat": 36.1193,
            "lon": -115.172
        },
        "venue": "Harrahs Cabaret at Harrahs Las Vegas",
        "images": {
            "huge": "https://seatgeek.com/images/performers-landscape/menopause-the-musical-6abdab/5966/huge.jpg"
        },
        "date_time_local": "2022-06-21T16:00:00",
        "tbd": false,
        "performers_name": "Menopause The Musical",
        "state": "NV",
        "url": "/5528083",
        "price": [
            39.7,
            86.4,
            46.4,
            82.9
        ]
    },
    {
        "id": 5713495,
        "title": "Micro Wrestling - Gowen",
        "category": "tiyatro",
        "address": null,
        "location": {
            "lat": 43.2517,
            "lon": -85.302
        },
        "venue": "Montcalm County Fairgrounds",
        "images": {
            "huge": "https://seatgeek.com/images/performers-landscape/micro-wrestling-2a8f46/754755/huge.jpg"
        },
        "date_time_local": "2022-06-21T19:00:00",
        "tbd": false,
        "performers_name": "Micro Wrestling",
        "state": "MI",
        "url": "/5713495",
        "price": [
            29.0,
            24.9,
            30.5
        ]
    },
    {
        "id": 5675357,
        "title": "Masters of Illusion - Atlantic City",
        "category": "tiyatro",
        "address": "777 Harrah's Boulevard",
        "location": {
            "lat": 39.3842,
            "lon": -74.4285
        },
        "venue": "Harrah's Resort Atlantic City",
        "images": {
            "huge": "https://seatgeek.com/images/performers-landscape/masters-of-illusion-0828d1/11699/huge.jpg"
        },
        "date_time_local": "2022-06-21T19:00:00",
        "tbd": false,
        "performers_name": "Masters of Illusion",
        "state": "NJ",
        "url": "/5675357",
        "price": [
            58.4,
            87.4,
            55.1
        ]
    },
    {
        "id": 5597647,
        "title": "Little Shop of Horrors - New York",
        "category": "tiyatro",
        "address": "407 West 43rd Street",
        "location": {
            "lat": 40.7593,
            "lon": -73.9927
        },
        "venue": "Westside Theatre Upstairs",
        "images": {
            "huge": "https://seatgeek.com/images/performers-landscape/little-shop-of-horrors-c8273e/8418/huge.jpg"
        },
        "date_time_local": "2022-06-21T19:00:00",
        "tbd": false,
        "performers_name": "Little Shop of Horrors",
        "state": "NY",
        "url": "/5597647",
        "price": [
            25.5,
            56.6,
            39.2
        ]
    },
    {
        "id": 5520052,
        "title": "Frederic Da Silva - Las Vegas",
        "category": "tiyatro",
        "address": "3645 South Las Vegas Boulevard",
        "location": {
            "lat": 36.1142,
            "lon": -115.171
        },
        "venue": "The Magic Attic at Bally's Las Vegas",
        "images": {
            "huge": "https://seatgeek.com/images/performers-landscape/frederic-da-silva-805092/297202/huge.jpg"
        },
        "date_time_local": "2022-06-21T16:00:00",
        "tbd": false,
        "performers_name": "Frederic Da Silva",
        "state": "NV",
        "url": "/5520052",
        "price": [
            86.6,
            26.8,
            34.4,
            78.5,
            68.4
        ]
    },
    {
        "id": 5402062,
        "title": "Come From Away - New York",
        "category": "tiyatro",
        "address": "236 West 45th Street",
        "location": {
            "lat": 40.7587,
            "lon": -73.9873
        },
        "venue": "Gerald Schoenfeld Theatre",
        "images": {
            "huge": "https://seatgeek.com/images/performers-landscape/come-from-away-a9a0d4/406007/huge.jpg"
        },
        "date_time_local": "2022-06-21T19:00:00",
        "tbd": false,
        "performers_name": "Come From Away",
        "state": "NY",
        "url": "/5402062",
        "price": [
            27.3,
            81.7
        ]
    },
    {
        "id": 5383628,
        "title": "Hadestown",
        "category": "tiyatro",
        "address": "219 West 48th Street",
        "location": {
            "lat": 40.7605,
            "lon": -73.9857
        },
        "venue": "Walter Kerr Theatre",
        "images": {
            "huge": "https://seatgeek.com/images/performers-landscape/hadestown-200a61/510834/huge.jpg"
        },
        "date_time_local": "2022-06-21T19:00:00",
        "tbd": false,
        "performers_name": "Hadestown",
        "state": "NY",
        "url": "/5383628",
        "price": [
            34.3,
            85.3,
            27.1,
            73.2
        ]
    },
    {
        "id": 5405951,
        "title": "The Lion King - New York",
        "category": "tiyatro",
        "address": "200 West 45th Street",
        "location": {
            "lat": 40.7579,
            "lon": -73.9862
        },
        "venue": "Minskoff Theatre",
        "images": {
            "huge": "https://seatgeek.com/images/performers-landscape/the-lion-king-0b52ab/5475/huge.jpg"
        },
        "date_time_local": "2022-06-21T19:00:00",
        "tbd": false,
        "performers_name": "The Lion King",
        "state": "NY",
        "url": "/5405951",
        "price": [
            31.0
        ]
    },
    {
        "id": 5553258,
        "title": "Nathan Burton - Las Vegas",
        "category": "tiyatro",
        "address": "3663 South Las Vegas Boulevard",
        "location": {
            "lat": 36.1096,
            "lon": -115.172
        },
        "venue": "Saxe Theater",
        "images": {
            "huge": "https://seatgeek.com/images/performers-landscape/nathan-burton-1279c7/8321/huge.jpg"
        },
        "date_time_local": "2022-06-21T16:00:00",
        "tbd": false,
        "performers_name": "Nathan Burton",
        "state": "NV",
        "url": "/5553258",
        "price": [
            26.7,
            87.5,
            28.7,
            21.0,
            44.7
        ]
    },
    {
        "id": 5587994,
        "title": "Harry Potter and the Cursed Child Toronto",
        "category": "tiyatro",
        "address": "244 Victoria St",
        "location": {
            "lat": 43.6554,
            "lon": -79.3795
        },
        "venue": "Ed Mirvish Theatre",
        "images": {
            "huge": "https://seatgeek.com/images/performers-landscape/harry-potter-and-the-cursed-child-e953ac/380245/huge.jpg"
        },
        "date_time_local": "2022-06-21T19:00:00",
        "tbd": false,
        "performers_name": "Harry Potter and The Cursed Child",
        "state": "ON",
        "url": "/5587994",
        "price": [
            89.0,
            55.9,
            29.3
        ]
    },
    {
        "id": 5681140,
        "title": "Moulin Rouge! The Musical VIP Room Experience",
        "category": "tiyatro",
        "address": "302 West 45th Street",
        "location": {
            "lat": 40.7594,
            "lon": -73.9891
        },
        "venue": "Al Hirschfeld Theatre",
        "images": {
            "huge": "https://seatgeek.com/images/performers-landscape/moulin-rouge-the-musical-vip-room-experience-53b56e/795845/huge.jpg"
        },
        "date_time_local": "2022-06-21T19:00:00",
        "tbd": false,
        "performers_name": "Moulin Rouge! The Musical VIP Room Experience",
        "state": "NY",
        "url": "/5681140",
        "price": [
            41.1,
            56.0,
            35.2,
            29.7
        ]
    },
    {
        "id": 5540976,
        "title": "The Minutes - New York",
        "category": "tiyatro",
        "address": "254 West 54th Street",
        "location": {
            "lat": 40.7644,
            "lon": -73.9838
        },
        "venue": "Studio 54",
        "images": {},
        "date_time_local": "2022-06-21T19:00:00",
        "tbd": false,
        "performers_name": "The Minutes (Play)",
        "state": "NY",
        "url": "/5540976",
        "price": [
            75.1,
            56.4,
            55.1,
            53.4
        ]
    },
    {
        "id": 5405598,
        "title": "Aladdin - New York",
        "category": "tiyatro",
        "address": "214 West 42nd Street",
        "location": {
            "lat": 40.7563,
            "lon": -73.9877
        },
        "venue": "New Amsterdam Theatre",
        "images": {
            "huge": "https://seatgeek.com/images/performers-landscape/aladdin-004f6c/11603/huge.jpg"
        },
        "date_time_local": "2022-06-21T19:00:00",
        "tbd": false,
        "performers_name": "Aladdin",
        "state": "NY",
        "url": "/5405598",
        "price": [
            37.0,
            28.5
        ]
    },
    {
        "id": 5565868,
        "title": "Chicago (Musical) - New York",
        "category": "tiyatro",
        "address": "219 West 49th Street",
        "location": {
            "lat": 40.7613,
            "lon": -73.985
        },
        "venue": "Ambassador Theatre",
        "images": {
            "huge": "https://seatgeek.com/images/performers-landscape/chicago-musical-03a650/5345/huge.jpg"
        },
        "date_time_local": "2022-06-21T19:00:00",
        "tbd": false,
        "performers_name": "Chicago (Musical)",
        "state": "NY",
        "url": "/5565868",
        "price": [
            53.3,
            85.8,
            33.6,
            82.2,
            68.2
        ]
    },
    {
        "id": 5634023,
        "title": "Hamilton - New York",
        "category": "tiyatro",
        "address": "226 West 46th Street",
        "location": {
            "lat": 40.7592,
            "lon": -73.9866
        },
        "venue": "Richard Rodgers Theatre",
        "images": {
            "huge": "https://seatgeek.com/images/performers-landscape/hamilton-328ab3/97669/huge.jpg"
        },
        "date_time_local": "2022-06-21T19:00:00",
        "tbd": false,
        "performers_name": "Hamilton",
        "state": "NY",
        "url": "/5634023",
        "price": [
            54.7,
            26.4,
            41.4,
            23.6
        ]
    },
    {
        "id": 5689383,
        "title": "Game Grumps",
        "category": "komedi",
        "address": "265 Tremont Street",
        "location": {
            "lat": 42.3504,
            "lon": -71.0654
        },
        "venue": "Shubert Theatre - MA",
        "images": {
            "huge": "https://seatgeek.com/images/performers-landscape/game-grumps-0a6aa3/446768/huge.jpg"
        },
        "date_time_local": "2022-06-21T20:00:00",
        "tbd": false,
        "performers_name": "Game Grumps",
        "state": "MA",
        "url": "/5689383",
        "price": [
            89.3,
            86.6
        ]
    },
    {
        "id": 5726853,
        "title": "Borgata Comedy Club",
        "category": "komedi",
        "address": "1 Borgata Way",
        "location": {
            "lat": 39.3781,
            "lon": -74.4338
        },
        "venue": "Music Box at the Borgata",
        "images": {},
        "date_time_local": "2022-06-21T20:00:00",
        "tbd": false,
        "performers_name": "Borgata Comedy Club",
        "state": "NJ",
        "url": "/5726853",
        "price": [
            51.6
        ]
    },
    {
        "id": 5534796,
        "title": "Lise Dion",
        "category": "komedi",
        "address": "6000 Boulevard Rome",
        "location": {
            "lat": 45.4413,
            "lon": -73.4404
        },
        "venue": "L`Etoile Banque Nationale",
        "images": {},
        "date_time_local": "2022-06-21T20:00:00",
        "tbd": false,
        "performers_name": "Lise Dion",
        "state": "QC",
        "url": "/5534796",
        "price": [
            41.1,
            41.8,
            78.6,
            68.3
        ]
    },
    {
        "id": 5652086,
        "title": "Chris Rock",
        "category": "komedi",
        "address": "700 14th Street",
        "location": {
            "lat": 39.7417,
            "lon": -104.998
        },
        "venue": "Bellco Theatre",
        "images": {
            "huge": "https://seatgeek.com/images/performers-landscape/chris-rock-7822f0/100595/18999/huge.jpg"
        },
        "date_time_local": "2022-06-21T19:00:00",
        "tbd": false,
        "performers_name": "Chris Rock",
        "state": "CO",
        "url": "/5652086",
        "price": [
            68.5,
            73.0
        ]
    },
    {
        "id": 5661514,
        "title": "The Best of the Second City",
        "category": "komedi",
        "address": "1616 N. Wells St",
        "location": {
            "lat": 41.9116,
            "lon": -87.635
        },
        "venue": "The Second City Mainstage Theatre",
        "images": {
            "huge": "https://seatgeek.com/images/performers-landscape/the-best-of-the-second-city-29332e/584020/huge.jpg"
        },
        "date_time_local": "2022-06-21T20:00:00",
        "tbd": false,
        "performers_name": "The Best of the Second City",
        "state": "IL",
        "url": "/5661514",
        "price": [
            52.1,
            88.3
        ]
    },
    {
        "id": 5675113,
        "title": "Tenacious D with Puddles Pity Party",
        "category": "komedi",
        "address": "14111 N.E. 145th Street",
        "location": {
            "lat": 47.7298,
            "lon": -122.149
        },
        "venue": "Chateau Ste Michelle Winery",
        "images": {
            "huge": "https://seatgeek.com/images/performers-landscape/tenacious-d-253621/1753/huge.jpg"
        },
        "date_time_local": "2022-06-21T19:00:00",
        "tbd": false,
        "performers_name": "Tenacious D",
        "state": "WA",
        "url": "/5675113",
        "price": [
            37.9,
            32.5,
            50.9
        ]
    },
    {
        "id": 5526820,
        "title": "Comedy Cellar",
        "category": "komedi",
        "address": "3700 W Flamingo Rd",
        "location": {
            "lat": 36.117,
            "lon": -115.186
        },
        "venue": "Comedy Cellar at Rio Las Vegas",
        "images": {},
        "date_time_local": "2022-06-21T19:00:00",
        "tbd": false,
        "performers_name": "Comedy Cellar",
        "state": "NV",
        "url": "/5526820",
        "price": [
            41.5,
            45.4,
            28.2
        ]
    },
    {
        "id": 5665501,
        "title": "Chicago Underground Comedy",
        "category": "komedi",
        "address": "2100 West Belmont Avenue",
        "location": {
            "lat": 41.9396,
            "lon": -87.681
        },
        "venue": "Beat Kitchen",
        "images": {
            "huge": "https://seatgeek.com/images/performers-landscape/chicago-underground-comedy-6bd309/13297/huge.jpg"
        },
        "date_time_local": "2022-06-21T21:00:00",
        "tbd": false,
        "performers_name": "Chicago Underground Comedy",
        "state": "IL",
        "url": "/5665501",
        "price": [
            21.5,
            38.4,
            89.7
        ]
    },
    {
        "id": 5548112,
        "title": "Terry Fator",
        "category": "komedi",
        "address": "3790 South Las Vegas Boulevard",
        "location": {
            "lat": 36.1645,
            "lon": -115.158
        },
        "venue": "Liberty Loft",
        "images": {
            "huge": "https://seatgeek.com/images/performers-landscape/terry-fator-7f4688/5214/17923/huge.jpg"
        },
        "date_time_local": "2022-06-21T19:30:00",
        "tbd": false,
        "performers_name": "Terry Fator",
        "state": "NV",
        "url": "/5548112",
        "price": [
            90.3
        ]
    },
    {
        "id": 5525965,
        "title": "Carrot Top",
        "category": "komedi",
        "address": "3900 Las Vegas Blvd Soouth",
        "location": {
            "lat": 36.0955,
            "lon": -115.176
        },
        "venue": "Atrium Showroom at Luxor Hotel and Casino",
        "images": {
            "huge": "https://seatgeek.com/images/performers-landscape/carrot-top-53c246/5190/huge.jpg"
        },
        "date_time_local": "2022-06-21T20:00:00",
        "tbd": false,
        "performers_name": "Carrot Top",
        "state": "NV",
        "url": "/5525965",
        "price": [
            56.9
        ]
    },
    {
        "id": 5615537,
        "title": "Eddie Griffin",
        "category": "komedi",
        "address": "2535 Las Vegas Blvd South",
        "location": {
            "lat": 36.142,
            "lon": -115.158
        },
        "venue": "Sahara Hotel and Casino",
        "images": {
            "huge": "https://seatgeek.com/images/performers-landscape/eddie-griffin-af414e/6741/17266/huge.jpg"
        },
        "date_time_local": "2022-06-21T20:00:00",
        "tbd": false,
        "performers_name": "Eddie Griffin",
        "state": "NV",
        "url": "/5615537",
        "price": [
            45.1,
            52.0,
            49.4
        ]
    },
    {
        "id": 5655312,
        "title": "Brad Garrett with Quinn Dahle",
        "category": "komedi",
        "address": "3799 Las Vegas Blvd South",
        "location": {
            "lat": 36.1022,
            "lon": -115.17
        },
        "venue": "Brad Garrett Comedy Club at MGM Grand Hotel and Casino",
        "images": {
            "huge": "https://seatgeek.com/images/performers-landscape/brad-garrett-744b44/5468/huge.jpg"
        },
        "date_time_local": "2022-06-21T20:00:00",
        "tbd": false,
        "performers_name": "Brad Garrett",
        "state": "NV",
        "url": "/5655312",
        "price": [
            34.6,
            73.3,
            74.0,
            38.7
        ]
    },
    {
        "id": 5528864,
        "title": "Laugh Factory Las Vegas",
        "category": "komedi",
        "address": "3801 Las Vegas Blvd.",
        "location": {
            "lat": 36.0996,
            "lon": -115.171
        },
        "venue": "Laugh Factory at Tropicana Resort & Casino",
        "images": {},
        "date_time_local": "2022-06-21T20:30:00",
        "tbd": false,
        "performers_name": "Laugh Factory Las Vegas",
        "state": "NV",
        "url": "/5528864",
        "price": [
            23.4,
            37.5,
            31.1,
            80.7
        ]
    },
    {
        "id": 5617688,
        "title": "Laugh Factory",
        "category": "komedi",
        "address": "3801 Las Vegas Boulevard",
        "location": {
            "lat": 36.1,
            "lon": -115.17
        },
        "venue": "Laugh Factory Tropicana",
        "images": {
            "huge": "https://seatgeek.com/images/performers-landscape/laugh-factory-4257e2/288982/huge.jpg"
        },
        "date_time_local": "2022-06-21T20:30:00",
        "tbd": false,
        "performers_name": "Laugh Factory",
        "state": "NV",
        "url": "/5617688",
        "price": [
            63.2
        ]
    },
    {
        "id": 5526980,
        "title": "Comedy Cellar",
        "category": "komedi",
        "address": "3700 W Flamingo Rd",
        "location": {
            "lat": 36.117,
            "lon": -115.186
        },
        "venue": "Comedy Cellar at Rio Las Vegas",
        "images": {},
        "date_time_local": "2022-06-21T21:30:00",
        "tbd": false,
        "performers_name": "Comedy Cellar",
        "state": "NV",
        "url": "/5526980",
        "price": [
            82.8,
            58.0
        ]
    },
    {
        "id": 5529319,
        "title": "Laugh Factory Las Vegas",
        "category": "komedi",
        "address": "3801 Las Vegas Blvd.",
        "location": {
            "lat": 36.0996,
            "lon": -115.171
        },
        "venue": "Laugh Factory at Tropicana Resort & Casino",
        "images": {},
        "date_time_local": "2022-06-21T22:30:00",
        "tbd": false,
        "performers_name": "Laugh Factory Las Vegas",
        "state": "NV",
        "url": "/5529319",
        "price": [
            54.2
        ]
    },
    {
        "id": 5502414,
        "title": "Mac King",
        "category": "komedi",
        "address": "3850 Las Vegas Blvd",
        "location": {
            "lat": 36.1,
            "lon": -115.17
        },
        "venue": "Tournament of Kings Arena at Excalibur Hotel and Casino",
        "images": {
            "huge": "https://seatgeek.com/images/performers-landscape/mac-king-3c4d1a/16551/5707/huge.jpg"
        },
        "date_time_local": "2022-06-22T13:00:00",
        "tbd": false,
        "performers_name": "Mac King",
        "state": "NV",
        "url": "/5502414",
        "price": [
            72.9,
            88.3,
            28.5,
            68.5,
            77.5
        ]
    },
    {
        "id": 5502412,
        "title": "Mac King",
        "category": "komedi",
        "address": "3850 Las Vegas Blvd",
        "location": {
            "lat": 36.1,
            "lon": -115.17
        },
        "venue": "Tournament of Kings Arena at Excalibur Hotel and Casino",
        "images": {
            "huge": "https://seatgeek.com/images/performers-landscape/mac-king-3c4d1a/16551/5707/huge.jpg"
        },
        "date_time_local": "2022-06-22T15:00:00",
        "tbd": false,
        "performers_name": "Mac King",
        "state": "NV",
        "url": "/5502412",
        "price": [
            72.5,
            48.9
        ]
    },
    {
        "id": 5705782,
        "title": "Rob Schneider",
        "category": "komedi",
        "address": "2500 Vanderbilt Beach Rd",
        "location": {
            "lat": 26.2426,
            "lon": -81.7652
        },
        "venue": "Off the Hook Comedy Club",
        "images": {
            "huge": "https://seatgeek.com/images/performers-landscape/rob-schneider-350fa5/5210/huge.jpg"
        },
        "date_time_local": "2022-06-22T18:30:00",
        "tbd": false,
        "performers_name": "Rob Schneider",
        "state": "Florida (fl)",
        "url": "/5705782",
        "price": [
            23.8,
            21.2
        ]
    },
    {
        "id": 5590838,
        "title": "Louis Jose Houde",
        "category": "komedi",
        "address": "1004 Rue Saint Catherine Street",
        "location": {
            "lat": 45.5004,
            "lon": -73.572
        },
        "venue": "L'Olympia (Olympia Theatre)",
        "images": {},
        "date_time_local": "2022-06-22T19:00:00",
        "tbd": false,
        "performers_name": "Louis Jose Houde",
        "state": "QC",
        "url": "/5590838",
        "price": [
            74.0,
            49.0
        ]
    },
    {
        "id": 5676606,
        "title": "Chelcie Lynn",
        "category": "komedi",
        "address": "401 W Short St",
        "location": {
            "lat": 38.0495,
            "lon": -84.4991
        },
        "venue": "Lexington Opera House",
        "images": {
            "huge": "https://seatgeek.com/images/performers-landscape/chelcie-lynn-35f745/797251/huge.jpg"
        },
        "date_time_local": "2022-06-22T19:00:00",
        "tbd": false,
        "performers_name": "Chelcie Lynn",
        "state": "KY",
        "url": "/5676606",
        "price": [
            66.3,
            90.5,
            53.0,
            31.5
        ]
    },
    {
        "id": 5626197,
        "title": "Nikki Glaser",
        "category": "komedi",
        "address": "5000 Euclid Avenue",
        "location": {
            "lat": 41.5036,
            "lon": -81.6538
        },
        "venue": "Agora Theatre",
        "images": {
            "huge": "https://seatgeek.com/images/performers-landscape/nikki-glaser-ce6b55/18761/19458/huge.jpg"
        },
        "date_time_local": "2022-06-22T19:00:00",
        "tbd": false,
        "performers_name": "Nikki Glaser",
        "state": "OH",
        "url": "/5626197",
        "price": [
            53.6,
            80.3
        ]
    },
    {
        "id": 5689384,
        "title": "Game Grumps",
        "category": "komedi",
        "address": "71 Eagle Street",
        "location": {
            "lat": 42.6504,
            "lon": -73.7584
        },
        "venue": "The Egg",
        "images": {
            "huge": "https://seatgeek.com/images/performers-landscape/game-grumps-0a6aa3/446768/huge.jpg"
        },
        "date_time_local": "2022-06-22T20:00:00",
        "tbd": false,
        "performers_name": "Game Grumps",
        "state": "NY",
        "url": "/5689384",
        "price": [
            23.8
        ]
    },
    {
        "id": 5534795,
        "title": "Lise Dion",
        "category": "komedi",
        "address": "6000 Boulevard Rome",
        "location": {
            "lat": 45.4413,
            "lon": -73.4404
        },
        "venue": "L`Etoile Banque Nationale",
        "images": {},
        "date_time_local": "2022-06-22T20:00:00",
        "tbd": false,
        "performers_name": "Lise Dion",
        "state": "QC",
        "url": "/5534795",
        "price": [
            48.0,
            76.9
        ]
    },
    {
        "id": 5711275,
        "title": "John Crist",
        "category": "komedi",
        "address": "140 North 13th Street",
        "location": {
            "lat": 40.8141,
            "lon": -96.7026
        },
        "venue": "Rococo Theatre",
        "images": {
            "huge": "https://seatgeek.com/images/performers-landscape/john-crist-9017ed/255660/huge.jpg"
        },
        "date_time_local": "2022-06-22T19:00:00",
        "tbd": false,
        "performers_name": "John Crist",
        "state": "NE",
        "url": "/5711275",
        "price": [
            75.2,
            79.6,
            75.6
        ]
    },
    {
        "id": 5726821,
        "title": "Borgata Comedy Club",
        "category": "komedi",
        "address": "1 Borgata Way",
        "location": {
            "lat": 39.3781,
            "lon": -74.4338
        },
        "venue": "Music Box at the Borgata",
        "images": {},
        "date_time_local": "2022-06-22T20:00:00",
        "tbd": false,
        "performers_name": "Borgata Comedy Club",
        "state": "NJ",
        "url": "/5726821",
        "price": [
            32.4,
            29.2,
            72.5,
            80.6
        ]
    },
    {
        "id": 5661499,
        "title": "The Best of the Second City",
        "category": "komedi",
        "address": "1616 N. Wells St",
        "location": {
            "lat": 41.9116,
            "lon": -87.635
        },
        "venue": "The Second City Mainstage Theatre",
        "images": {
            "huge": "https://seatgeek.com/images/performers-landscape/the-best-of-the-second-city-29332e/584020/huge.jpg"
        },
        "date_time_local": "2022-06-22T20:00:00",
        "tbd": false,
        "performers_name": "The Best of the Second City",
        "state": "IL",
        "url": "/5661499",
        "price": [
            54.6,
            55.9
        ]
    }
]